jornadaRPA/__init__.py
jornadaRPA/webScrap/__init__.py
jornadaRPA/webScrap/webscrap.py
tests/__init__.py
tests/test_webscrap.py
JornadaRPA.WebScrap-0.1.2.dist-info/LICENSE
JornadaRPA.WebScrap-0.1.2.dist-info/METADATA
JornadaRPA.WebScrap-0.1.2.dist-info/WHEEL
JornadaRPA.WebScrap-0.1.2.dist-info/top_level.txt
JornadaRPA.WebScrap-0.1.2.dist-info/RECORD
