Metadata-Version: 2.1
Name: JornadaRPA.WebScrap
Version: 0.1.2
Summary: Módulo de scraping de tabelas web para o JornadaRPA
Home-page: https://github.com/JornadaRPA/JornadaRPA.WebScrap
Author: Alex Diogo
Author-email: alexdiogo@desafiosrpa.com.br
Classifier: Programming Language :: Python :: 3
Classifier: License :: OSI Approved :: MIT License
Classifier: Operating System :: OS Independent
Requires-Python: >=3.6
License-File: LICENSE
Requires-Dist: botcity-framework-web
Requires-Dist: pandas
